vsdx/__init__.py
vsdx/connectors.py
vsdx/formulae.py
vsdx/geometry.py
vsdx/media.py
vsdx/pages.py
vsdx/shapes.py
vsdx/vsdxdiff.py
vsdx/vsdxfile.py
vsdx/media/media.vsdx
vsdx-0.6.1.dist-info/licenses/LICENSE
vsdx-0.6.1.dist-info/METADATA
vsdx-0.6.1.dist-info/WHEEL
vsdx-0.6.1.dist-info/top_level.txt
vsdx-0.6.1.dist-info/RECORD
