Metadata-Version: 2.4
Name: vsdx
Version: 0.6.1
Summary: vsdx - A python library for processing .vsdx files
Home-page: https://github.com/dave-howard/vsdx
Author: Dave Howard
Author-email: dave@codypy.com
Project-URL: Documentation, https://vsdx.readthedocs.io/en/latest/
Classifier: Programming Language :: Python :: 3.8
Classifier: Programming Language :: Python :: 3.9
Classifier: Programming Language :: Python :: 3.10
Classifier: Programming Language :: Python :: 3.11
Classifier: Programming Language :: Python :: 3.12
Classifier: Programming Language :: Python :: 3.13
Classifier: Programming Language :: Python :: 3.14
Classifier: License :: OSI Approved :: BSD License
Classifier: Operating System :: OS Independent
Classifier: Development Status :: 4 - Beta
Requires-Python: >=3.7
License-File: LICENSE
Requires-Dist: Jinja2
Requires-Dist: deprecation
Dynamic: author
Dynamic: author-email
Dynamic: classifier
Dynamic: description
Dynamic: description-content-type
Dynamic: home-page
Dynamic: license-file
Dynamic: project-url
Dynamic: requires-dist
Dynamic: requires-python
Dynamic: summary
